uganda_uber_switching_reg/__init__.py
uganda_uber_switching_reg/cm.py
uganda_uber_switching_reg/mle.py
uganda_uber_switching_reg/patches.py
uganda_uber_switching_reg/saved_models/plots/2_0.0_plot.png
uganda_uber_switching_reg/saved_models/plots/2_0.1_plot.png
uganda_uber_switching_reg/saved_models/plots/2_0.5_plot.png
uganda_uber_switching_reg/saved_models/plots/2_0.6_plot.png
uganda_uber_switching_reg/saved_models/plots/2_0.9_plot.png
uganda_uber_switching_reg/saved_models/plots/3_0.1_plot.png
uganda_uber_switching_reg/saved_models/plots/3_0.5_plot.png
uganda_uber_switching_reg/saved_models/plots/3_0.9_plot.png
uganda_uber_switching_reg/saved_models/plots/4_0.1_plot.png
uganda_uber_switching_reg/saved_models/plots/4_0.5_plot.png
uganda_uber_switching_reg/simulation/__init__.py
uganda_uber_switching_reg/simulation/data_creation.py
uganda_uber_switching_reg/simulation/monte_carlo.py
uganda_uber_switching_reg/simulation/regression.py
uganda_uber_switching_reg/simulation/utils.py
uganda_uber_switching_reg/simulation/visualization.py
uganda_uber_switching_reg/uganda-uber-paper.code-workspace
uganda_uber_switching_reg-0.4.8.dist-info/WHEEL
uganda_uber_switching_reg-0.4.8.dist-info/METADATA
uganda_uber_switching_reg-0.4.8.dist-info/RECORD
